remnapy/__init__.py
remnapy/controllers/__init__.py
remnapy/controllers/api_tokens_management.py
remnapy/controllers/auth.py
remnapy/controllers/bandwidthstats.py
remnapy/controllers/config_profiles.py
remnapy/controllers/external_squads.py
remnapy/controllers/hosts.py
remnapy/controllers/hosts_bulk_actions.py
remnapy/controllers/hwid.py
remnapy/controllers/inbounds.py
remnapy/controllers/inbounds_bulk_actions.py
remnapy/controllers/infra_billing.py
remnapy/controllers/internal_squads.py
remnapy/controllers/keygen.py
remnapy/controllers/nodes.py
remnapy/controllers/nodes_usage_history.py
remnapy/controllers/passkeys.py
remnapy/controllers/remnawave_settings.py
remnapy/controllers/snippets.py
remnapy/controllers/subscription.py
remnapy/controllers/subscriptions_controller.py
remnapy/controllers/subscriptions_request.py
remnapy/controllers/subscriptions_settings.py
remnapy/controllers/subscriptions_template.py
remnapy/controllers/system.py
remnapy/controllers/users.py
remnapy/controllers/users_bulk_actions.py
remnapy/controllers/users_stats.py
remnapy/controllers/webhooks.py
remnapy/controllers/xray_config.py
remnapy/enums/__init__.py
remnapy/enums/alpn.py
remnapy/enums/auth.py
remnapy/enums/client_type.py
remnapy/enums/error_code.py
remnapy/enums/fingerprint.py
remnapy/enums/security_layer.py
remnapy/enums/subscriptions_settings.py
remnapy/enums/template_type.py
remnapy/enums/users.py
remnapy/enums/webhook.py
remnapy/exceptions/__init__.py
remnapy/exceptions/general.py
remnapy/exceptions/handler.py
remnapy/models/__init__.py
remnapy/models/api_tokens_management.py
remnapy/models/auth.py
remnapy/models/bandwidthstats.py
remnapy/models/config_profiles.py
remnapy/models/external_squads.py
remnapy/models/hosts.py
remnapy/models/hosts_bulk_actions.py
remnapy/models/hwid.py
remnapy/models/inbounds.py
remnapy/models/inbounds_bulk_actions.py
remnapy/models/infra_billing.py
remnapy/models/internal_squads.py
remnapy/models/keygen.py
remnapy/models/nodes.py
remnapy-2.3.3.dist-info/licenses/LICENSE
remnapy-2.3.3.dist-info/METADATA
remnapy-2.3.3.dist-info/WHEEL
remnapy-2.3.3.dist-info/top_level.txt
remnapy-2.3.3.dist-info/RECORD
