Metadata-Version: 2.4
Name: remnapy
Version: 2.3.3
Summary: A Python SDK for interacting with the Remnawave API v2.3.0.
Author: snoups
Author-email: Artem <dev@forestsnet.com>
License-Expression: MIT
Project-URL: PanelPage, https://remna.st/
Project-URL: CommunityChat, https://t.me/+xQs17zMzwCY1NzYy
Project-URL: UpdateChannel, https://t.me/remnawave
Project-URL: RemnashopPage, http://www.github.com/snoups/remnashop
Project-URL: RemnashopChat, https://t.me/remna_shop
Project-URL: Homepage, https://github.com/snoups/remnapy
Keywords: remnawave,api,sdk,proxy,httpx,async,xray
Classifier: Development Status :: 5 - Production/Stable
Classifier: Intended Audience :: Developers
Classifier: Natural Language :: English
Classifier: Programming Language :: Python :: 3.11
Classifier: Programming Language :: Python :: 3.12
Classifier: Programming Language :: Python :: 3.13
Classifier: Programming Language :: Python :: Implementation :: CPython
Classifier: Programming Language :: Python :: Implementation :: PyPy
Classifier: Framework :: AsyncIO
Requires-Python: <4.0,>=3.11
License-File: LICENSE
Requires-Dist: rapid-api-client==0.6.0
Requires-Dist: orjson<4.0.0,>=3.10.15
Requires-Dist: httpx<0.28.0,>=0.27.2
Requires-Dist: pydantic[email]<3.0.0,>=2.9.2
Requires-Dist: pydantic-core<2.34.0,>=2.33.1
Requires-Dist: pydantic<3.0.0,>=2.9.2
Requires-Dist: cryptography<47.0.0,>=46.0.3
Dynamic: license-file
